mathhunt/__init__.py
mathhunt/__data/__init__.py
mathhunt/__data/bradis_table.json
mathhunt/functions/__init__.py
mathhunt/functions/functions.py
mathhunt/geometry/__init__.py
mathhunt/geometry/distances.py
mathhunt/geometry/shapes.py
mathhunt/logic/__init__.py
mathhunt/logic/logic.py
mathhunt/probability/__init__.py
mathhunt/probability/experiments.py
mathhunt/probability/functions.py
mathhunt/viz/__init__.py
mathhunt/viz/animations.py
mathhunt/viz/core.py
mathhunt/viz/functions.py
mathhunt-0.5.0.dist-info/METADATA
mathhunt-0.5.0.dist-info/WHEEL
mathhunt-0.5.0.dist-info/top_level.txt
mathhunt-0.5.0.dist-info/RECORD
