Metadata-Version: 2.4
Name: mathhunt
Version: 0.5.0
Summary: Toolkit for math calculations.
Home-page: https://github.com/Matvei-Antipov/mathhunt-0.1.0.git
Author: Matvei Antipov
Author-email: matveiantipov2007@gmail.com
License: MIT
Classifier: Programming Language :: Python :: 3
Classifier: License :: OSI Approved :: MIT License
Classifier: Operating System :: OS Independent
Requires-Python: >=3.6
Requires-Dist: numpy
Requires-Dist: matplotlib
Dynamic: author
Dynamic: author-email
Dynamic: classifier
Dynamic: home-page
Dynamic: license
Dynamic: requires-python
Dynamic: summary
